fpgen/__init__.py
fpgen/__main__.py
fpgen/bayesian_network.py
fpgen/exceptions.py
fpgen/generator.py
fpgen/pkgman.py
fpgen/py.typed
fpgen/structs.py
fpgen/trace.py
fpgen/unpacker.py
fpgen/utils.py
fpgen-1.3.0.dist-info/LICENSE
fpgen-1.3.0.dist-info/METADATA
fpgen-1.3.0.dist-info/WHEEL
fpgen-1.3.0.dist-info/entry_points.txt
fpgen-1.3.0.dist-info/RECORD
