Metadata-Version: 2.3
Name: fpgen
Version: 1.3.0
Summary: A fast & comprehensive browser fingerprint generator
License: Apache-2.0
Keywords: client,headers,fingerprint,generator,browser,http,scraping,requests,playwright
Author: daijro
Author-email: daijro.dev@gmail.com
Requires-Python: >=3.8,<4.0
Classifier: License :: OSI Approved :: Apache Software License
Classifier: Programming Language :: Python :: 3
Classifier: Programming Language :: Python :: 3.8
Classifier: Programming Language :: Python :: 3.9
Classifier: Programming Language :: Python :: 3.10
Classifier: Programming Language :: Python :: 3.11
Classifier: Programming Language :: Python :: 3.12
Classifier: Programming Language :: Python :: 3.13
Classifier: Topic :: Internet :: WWW/HTTP
Classifier: Topic :: Internet :: WWW/HTTP :: Browsers
Classifier: Topic :: Software Development :: Libraries :: Python Modules
Requires-Dist: click
Requires-Dist: httpx
Requires-Dist: indexed-zstd
Requires-Dist: numpy
Requires-Dist: orjson
Requires-Dist: zstandard
Project-URL: Repository, https://github.com/scrapfly/fingerprint-generator
